fluxpart/__init__.py
fluxpart/__version__.py
fluxpart/api.py
fluxpart/constants.py
fluxpart/containers.py
fluxpart/fluxpart.py
fluxpart/hfdata.py
fluxpart/partition.py
fluxpart/util.py
fluxpart/wue.py
fluxpart-0.2.11.dist-info/AUTHORS.rst
fluxpart-0.2.11.dist-info/LICENSE
fluxpart-0.2.11.dist-info/METADATA
fluxpart-0.2.11.dist-info/WHEEL
fluxpart-0.2.11.dist-info/top_level.txt
fluxpart-0.2.11.dist-info/RECORD
